qroestl/__init__.py
qroestl/backends/Braket.py
qroestl/backends/Cplex.py
qroestl/backends/Gurobi.py
qroestl/backends/Ocean.py
qroestl/backends/Qiskit.py
qroestl/backends/__init__.py
qroestl/model/Model.py
qroestl/model/__init__.py
qroestl/problems/ExactCover.py
qroestl/problems/MCMTWB_k_MaxCover.py
qroestl/problems/MCMTW_MaxCoverage.py
qroestl/problems/MPCMTWB_k_MaxCover.py
qroestl/problems/MaxCoverH1.py
qroestl/problems/MaxCoverage.py
qroestl/problems/SetCover.py
qroestl/problems/SetCoverUnconstrained.py
qroestl/problems/__init__.py
qroestl/utils/SaveIBMQToken.py
qroestl/utils/Utils.py
qroestl/utils/__init__.py
run/BackendConfig.py
run/CollapseTest.py
run/CompareGreedy.py
run/Draw.py
run/Main.py
run/TaskConfig.py
run/TimeLimitRun.py
run/__init__.py
Qroestl-0.2.2.dist-info/LICENSE
Qroestl-0.2.2.dist-info/METADATA
Qroestl-0.2.2.dist-info/WHEEL
Qroestl-0.2.2.dist-info/top_level.txt
Qroestl-0.2.2.dist-info/RECORD
