Metadata-Version: 2.1
Name: Qroestl
Version: 0.2.2
Summary: A thin optimization layer on top of Qiskit.
Home-page: https://github.com/ssenge/Qroestl
Author: Sebastian Senge
Author-email: ssenge.public@gmail.com
Classifier: Programming Language :: Python :: 3
Classifier: License :: OSI Approved :: GNU General Public License v3 (GPLv3)
Classifier: Operating System :: OS Independent
Requires-Python: >=3.8
License-File: LICENSE
